README.md
setup.cfg
setup.py
multiprocessing_dag/__init__.py
multiprocessing_dag.egg-info/PKG-INFO
multiprocessing_dag.egg-info/SOURCES.txt
multiprocessing_dag.egg-info/dependency_links.txt
multiprocessing_dag.egg-info/top_level.txt